treinar_modelos_pns_2019/__init__.py
treinar_modelos_pns_2019/funcoes.py
treinar_modelos_pns_2019-0.0.8.dist-info/METADATA
treinar_modelos_pns_2019-0.0.8.dist-info/WHEEL
treinar_modelos_pns_2019-0.0.8.dist-info/top_level.txt
treinar_modelos_pns_2019-0.0.8.dist-info/RECORD
