Metadata-Version: 2.4
Name: treinar_modelos_pns_2019
Version: 0.0.8
Summary: Pacote facilitador de criação de modelos
Author: Romario Gomes
Requires-Dist: pandas
Requires-Dist: numpy
Requires-Dist: scikit-learn
Requires-Dist: imbalanced-learn
Requires-Dist: optuna
Requires-Dist: scikit-optimize
Requires-Dist: catboost
Requires-Dist: xgboost
Requires-Dist: lightgbm
Requires-Dist: tabulate
Dynamic: author
Dynamic: description
Dynamic: requires-dist
Dynamic: summary
